divepy/AutoEDA.py
divepy/DataAnalyzer.py
divepy/DataLoader.py
divepy/DataVisualizer.py
divepy/EDAResults.py
divepy/LLMAnalyzer.py
divepy/ReportGenerator.py
divepy/__init__.py
divepy/run.py
divepy-0.1.2.dist-info/licenses/LICENSE
tests/__init__.py
tests/generate_test_data.py
tests/test_LLMAnalyzer.py
tests/data/generated_data.csv
utils/__init__.py
utils/logger.py
divepy-0.1.2.dist-info/METADATA
divepy-0.1.2.dist-info/WHEEL
divepy-0.1.2.dist-info/entry_points.txt
divepy-0.1.2.dist-info/top_level.txt
divepy-0.1.2.dist-info/RECORD
