Metadata-Version: 2.4
Name: divepy
Version: 0.1.2
Summary: Automated Exploratory Data Analysis (EDA) Tool
Home-page: https://github.com/AdwitaSingh1711/Auto-EDA
Author: Adwita Singh
Author-email: adwita.s.at07@gmail.com
Classifier: Programming Language :: Python :: 3
Classifier: License :: OSI Approved :: MIT License
Classifier: Operating System :: OS Independent
Requires-Python: >=3.8
License-File: LICENSE
Requires-Dist: pandas
Requires-Dist: numpy
Requires-Dist: plotly
Requires-Dist: loguru
Requires-Dist: ollama
Requires-Dist: scikit-learn
Requires-Dist: matplotlib
Requires-Dist: seaborn
Provides-Extra: test
Requires-Dist: pytest; extra == "test"
Dynamic: author
Dynamic: author-email
Dynamic: classifier
Dynamic: description
Dynamic: description-content-type
Dynamic: home-page
Dynamic: license-file
Dynamic: provides-extra
Dynamic: requires-dist
Dynamic: requires-python
Dynamic: summary
